{"name":"Simplerte","tagline":"","body":"simpleRTE\r\n=========\r\n\r\nThe minimalistic simple rich text editor.\r\n\r\n##Features\r\n\r\n* Bold\r\n* Italics\r\n* Underscore\r\n* Link\r\n* Image\r\n\r\n\r\n###How to Use\r\nYou can call the simpleRTE method on any jQuery selection. Any valid jQuery selectors will work. The only thing you need to have in your html page is a div element. the plugin will build the rich text editor and add as a child element to your div.\r\n\r\n\r\n#####Applying on a single element with ID attribute\r\n```javascript\r\n$(\"#yourElementID\").simpleRTE();\r\n```\r\n#####Applying on a multiple elements with css class\r\n```javascript\r\n$(\"div.yourDivIDclass\").simpleRTE();\r\n```","google":"","note":"Don't delete this file! It's used internally to help with page regeneration."}